{
  "_class": "text",
  "attributedString": {
    "_class": "attributedString",
    "attributes": [
      {
        "_class": "stringAttribute",
        "attributes": {
          "MSAttributedStringColorAttribute": {
            "_class": "color",
            "alpha": 1,
            "blue": 0.6509803921568628,
            "green": 0.6509803921568628,
            "red": 0.8392156862745098
          },
          "MSAttributedStringFontAttribute": {
            "_class": "fontDescriptor",
            "attributes": {
              "name": "HelveticaNeue-CondensedBold",
              "size": 230
            }
          },
          "kerning": 0,
          "paragraphStyle": {
            "_class": "paragraphStyle",
            "alignment": 0
          },
          "textStyleVerticalAlignmentKey": 0
        },
        "length": 5,
        "location": 0
      }
    ],
    "string": "NORMA"
  },
  "automaticallyDrawOnUnderlyingPath": false,
  "do_objectID": "A3C2BA6E-3F1C-48F3-988A-4285EB5C1198",
  "dontSynchroniseWithSymbol": false,
  "exportOptions": {
    "_class": "exportOptions",
    "do_objectID": "8490FE4C-2CC9-4FA7-B610-E0549C690670",
    "exportFormats": [
    ],
    "includedLayerIds": [
    ],
    "layerOptions": 0,
    "shouldTrim": false
  },
  "frame": {
    "_class": "rect",
    "constrainProportions": false,
    "do_objectID": "8846B946-3465-4AE3-B3DA-AB3B2A141AF6",
    "height": 272,
    "width": 686,
    "x": 86,
    "y": 197
  },
  "glyphBounds": "{{11, 53}, {675, 171}}",
  "isFlippedHorizontal": false,
  "isFlippedVertical": false,
  "isLocked": false,
  "isVisible": true,
  "layerListExpandedType": 0,
  "lineSpacingBehaviour": 2,
  "name": "NORMA",
  "nameIsFixed": false,
  "resizingConstraint": 47,
  "resizingType": 0,
  "rotation": 0,
  "shouldBreakMaskChain": false,
  "style": {
    "_class": "style",
    "do_objectID": "AAA781E1-4B4D-42AF-97C8-7A69866E0B05",
    "endDecorationType": 0,
    "miterLimit": 10,
    "shadows": [
      {
        "_class": "shadow",
        "blurRadius": 30,
        "color": {
          "_class": "color",
          "alpha": 1,
          "blue": 0,
          "green": 0,
          "red": 0
        },
        "contextSettings": {
          "_class": "graphicsContextSettings",
          "blendMode": 0,
          "opacity": 1
        },
        "isEnabled": true,
        "offsetX": 2,
        "offsetY": 2,
        "spread": 0
      }
    ],
    "startDecorationType": 0,
    "textStyle": {
      "_class": "textStyle",
      "do_objectID": "8D673AA7-B0B2-4EAD-BBE1-D23E93BD3ACC",
      "encodedAttributes": {
        "MSAttributedStringColorAttribute": {
          "_class": "color",
          "alpha": 1,
          "blue": 0.6509803921568628,
          "green": 0.6509803921568628,
          "red": 0.8392156862745098
        },
        "MSAttributedStringFontAttribute": {
          "_class": "fontDescriptor",
          "attributes": {
            "name": "HelveticaNeue-CondensedBold",
            "size": 230
          }
        },
        "kerning": 0,
        "paragraphStyle": {
          "_class": "paragraphStyle",
          "alignment": 0
        },
        "textStyleVerticalAlignmentKey": 0
      },
      "verticalAlignment": 0
    }
  },
  "textBehaviour": 0
}